spx17979/__init__.py
spx17979/py.typed
spx17979/spx17979.py
spx17979_driver-0.1.0.dist-info/LICENSE
spx17979_driver-0.1.0.dist-info/METADATA
spx17979_driver-0.1.0.dist-info/WHEEL
spx17979_driver-0.1.0.dist-info/top_level.txt
spx17979_driver-0.1.0.dist-info/zip-safe
spx17979_driver-0.1.0.dist-info/RECORD
