Metadata-Version: 2.1
Name: spx17979-driver
Version: 0.1.0
Summary: Python driver for the SparkFun SPX-17979 Qwiic Sound Trigger
Home-page: https://github.com/rogiervandergeer/spx17979-driver
Author: Rogier van der Geer
Author-email: rogier@vander-geer.nl
License: Apache License 2.0
Platform: UNKNOWN
Classifier: Programming Language :: Python :: 3
Classifier: License :: OSI Approved :: Apache Software License
Classifier: Topic :: System :: Hardware :: Hardware Drivers
Classifier: Typing :: Typed
License-File: LICENSE
Requires-Dist: pca9536-driver (>=0.1.1)
